<annotation>
	<folder>town01</folder>
	<filename>town01_00004900.png</filename>
	<path>/home/tanya/carla-dataset/done/town01/town01_00004900.png</path>
	<source>
		<database>Unknown</database>
	</source>
	<size>
		<width>640</width>
		<height>380</height>
		<depth>3</depth>
	</size>
	<segmented>0</segmented>
	<object>
		<name>pedestrian</name>
		<pose>Unspecified</pose>
		<truncated>0</truncated>
		<difficult>0</difficult>
		<bndbox>
			<xmin>142</xmin>
			<ymin>196</ymin>
			<xmax>155</xmax>
			<ymax>218</ymax>
		</bndbox>
	</object>
	<object>
		<name>vehicle</name>
		<pose>Unspecified</pose>
		<truncated>1</truncated>
		<difficult>0</difficult>
		<bndbox>
			<xmin>1</xmin>
			<ymin>209</ymin>
			<xmax>135</xmax>
			<ymax>333</ymax>
		</bndbox>
	</object>
	<object>
		<name>vehicle</name>
		<pose>Unspecified</pose>
		<truncated>0</truncated>
		<difficult>0</difficult>
		<bndbox>
			<xmin>131</xmin>
			<ymin>197</ymin>
			<xmax>231</xmax>
			<ymax>251</ymax>
		</bndbox>
	</object>
</annotation>
