<annotation>
	<folder>pre_processed</folder>
	<filename>town04_00061800.png</filename>
	<path>/home/tanya/carla-dataset/pre_processed/town04_00061800.png</path>
	<source>
		<database>Unknown</database>
	</source>
	<size>
		<width>640</width>
		<height>380</height>
		<depth>3</depth>
	</size>
	<segmented>0</segmented>
	<object>
		<name>vehicle</name>
		<pose>Unspecified</pose>
		<truncated>0</truncated>
		<difficult>0</difficult>
		<bndbox>
			<xmin>306</xmin>
			<ymin>191</ymin>
			<xmax>333</xmax>
			<ymax>211</ymax>
		</bndbox>
	</object>
	<object>
		<name>vehicle</name>
		<pose>Unspecified</pose>
		<truncated>0</truncated>
		<difficult>0</difficult>
		<bndbox>
			<xmin>381</xmin>
			<ymin>194</ymin>
			<xmax>398</xmax>
			<ymax>203</ymax>
		</bndbox>
	</object>
</annotation>
