<annotation>
	<folder>town03</folder>
	<filename>town03_00025800.png</filename>
	<path>/home/tanya/carla-dataset/done/town03/town03_00025800.png</path>
	<source>
		<database>Unknown</database>
	</source>
	<size>
		<width>640</width>
		<height>380</height>
		<depth>3</depth>
	</size>
	<segmented>0</segmented>
	<object>
		<name>vehicle</name>
		<pose>Unspecified</pose>
		<truncated>0</truncated>
		<difficult>0</difficult>
		<bndbox>
			<xmin>231</xmin>
			<ymin>204</ymin>
			<xmax>404</xmax>
			<ymax>353</ymax>
		</bndbox>
	</object>
	<object>
		<name>vehicle</name>
		<pose>Unspecified</pose>
		<truncated>0</truncated>
		<difficult>0</difficult>
		<bndbox>
			<xmin>298</xmin>
			<ymin>186</ymin>
			<xmax>341</xmax>
			<ymax>228</ymax>
		</bndbox>
	</object>
	<object>
		<name>vehicle</name>
		<pose>Unspecified</pose>
		<truncated>0</truncated>
		<difficult>0</difficult>
		<bndbox>
			<xmin>429</xmin>
			<ymin>196</ymin>
			<xmax>470</xmax>
			<ymax>212</ymax>
		</bndbox>
	</object>
	<object>
		<name>vehicle</name>
		<pose>Unspecified</pose>
		<truncated>0</truncated>
		<difficult>0</difficult>
		<bndbox>
			<xmin>212</xmin>
			<ymin>194</ymin>
			<xmax>233</xmax>
			<ymax>206</ymax>
		</bndbox>
	</object>
</annotation>
